examples/__init__.py
examples/create_flow.py
examples/delete_flow.py
examples/deprecate_flow.py
examples/get_flow_assets.py
examples/get_flow_details.py
examples/list_flows.py
examples/publish_flow.py
examples/send_published_flow.py
examples/send_unpublished_flow.py
examples/simulate_flow.py
examples/update_flow.py
examples/update_flow_json.py
examples/upload_flow_json.py
webhook/__init__.py
whatsapp_flows/__init__.py
whatsapp_flows-0.1.0.dist-info/LICENSE
whatsapp_flows-0.1.0.dist-info/METADATA
whatsapp_flows-0.1.0.dist-info/WHEEL
whatsapp_flows-0.1.0.dist-info/top_level.txt
whatsapp_flows-0.1.0.dist-info/RECORD
