Metadata-Version: 2.1
Name: whatsapp-flows
Version: 0.1.0
Summary: Opensource python wrapper for Meta Whatsapp Flows Cloud API
Home-page: https://github.com/misingo255/whatsapp-flows
Author: Wilbert Misingo
Author-email: wilbertmisingo@gmail.com
License: Apache
Keywords: Whatsapp,Whatsapp Flows,Whatsapp API,Whatsapp Python,Whatsapp Python API,Whatsapp Flows Python API
Classifier: Development Status :: 3 - Alpha
Classifier: Intended Audience :: Developers
Classifier: Topic :: Software Development :: Build Tools
Classifier: License :: OSI Approved :: Apache Software License
Classifier: Programming Language :: Python :: 3.8
Classifier: Programming Language :: Python :: 3.9
Classifier: Programming Language :: Python :: 3.10
Classifier: Programming Language :: Python :: 3.11
Classifier: Programming Language :: Python :: 3.12
Requires-Python: >=3.8
License-File: LICENSE
Requires-Dist: requests>=2.31.0
